botskeleton/__init__.py
botskeleton/botskeleton.py
botskeleton/error.py
botskeleton/outputs/__init__.py
botskeleton/outputs/output_birdsite.py
botskeleton/outputs/output_mastodon.py
botskeleton/outputs/output_utils.py
botskeleton/test/__init__.py
botskeleton/test/test_botskeleton.py
botskeleton/test/test_output_birdsite.py
botskeleton/test/test_output_mastodon.py
botskeleton-3.3.8.dist-info/LICENSE
botskeleton-3.3.8.dist-info/METADATA
botskeleton-3.3.8.dist-info/WHEEL
botskeleton-3.3.8.dist-info/top_level.txt
botskeleton-3.3.8.dist-info/RECORD
