Metadata-Version: 2.1
Name: botskeleton
Version: 3.3.8
Summary: A skeleton for content bots.
Home-page: https://github.com/lunemercove/botskeleton
Author: Luné Mercové
Author-email: pypi@lune.gay
License: BSD3
Classifier: Development Status :: 5 - Production/Stable
Classifier: Environment :: Console
Classifier: Intended Audience :: Developers
Classifier: License :: OSI Approved :: BSD License
Classifier: Natural Language :: English
Classifier: Operating System :: MacOS :: MacOS X
Classifier: Operating System :: POSIX :: Linux
Classifier: Operating System :: POSIX :: BSD :: FreeBSD
Classifier: Programming Language :: Python :: 3.6
Classifier: Programming Language :: Python :: 3.7
Classifier: Programming Language :: Python :: 3.8
Classifier: Programming Language :: Python :: 3.9
Classifier: Programming Language :: Python :: 3.10
Classifier: Programming Language :: Python :: 3 :: Only
Classifier: Programming Language :: Python :: Implementation :: CPython
Classifier: Topic :: Software Development :: Libraries
Classifier: Typing :: Typed
Requires-Python: >=3.6
License-File: LICENSE
Requires-Dist: clint (<0.6.0,>=0.5.1)
Requires-Dist: bottilities (<2.0.0,>=1.4.0)
Requires-Dist: tweepy (<5.0,>=4.12.0)
Requires-Dist: Mastodon.py (<2.0,>=1.5.1)
